{
    "CompUnits": {
        "amcQw_d": {
            "mod": "...MASTER...",
            "out": "objs/amcQw_d.o",
            "bytes": 8422,
            "mode": 4,
            "text": 527,
            "checksum": 0
        },
        "reYIK_d": {
            "cls": 7017,
            "mod": "std",
            "out": "reYIK_d.o",
            "bytes": 43064,
            "mode": 4,
            "text": 7325,
            "checksum": 0,
            "archive": "archive.0/_44089_archive_1.a"
        },
        "J54Lv_d": {
            "mod": "Mem1r1w",
            "out": "J54Lv_d.o",
            "bytes": 11574,
            "mode": 4,
            "text": 2854,
            "checksum": 0,
            "archive": "archive.0/_44089_archive_1.a"
        },
        "U3bwm_d": {
            "mod": "__simulation_def",
            "out": "U3bwm_d.o",
            "bytes": 9002,
            "mode": 4,
            "text": 499,
            "checksum": 0,
            "archive": "archive.0/_44089_archive_1.a"
        }
    },
    "Modules": {
        "std": {
            "start_perf": [
                0.32828998565673828,
                0.084695999999999994,
                0.039524999999999998,
                322548,
                322548,
                1665984529.6692419,
                894389836779523
            ],
            "child_modules": {},
            "Compiled": "Yes",
            "svclass": [
                "$vcs_nba_dyn_obj",
                576,
                35,
                2,
                2,
                0,
                "sigprop$$",
                576,
                35,
                2,
                2,
                0,
                "process",
                2380,
                200,
                8,
                8,
                0,
                "event",
                597,
                34,
                2,
                2,
                0,
                "mailbox",
                1769,
                140,
                9,
                9,
                0,
                "semaphore",
                1119,
                84,
                5,
                5,
                0
            ],
            "nRouts": 35,
            "Compiled Times": 1,
            "end_perf": [
                0.33717799186706543,
                0.092595999999999998,
                0.040509999999999997,
                323512,
                323512,
                894389868937763,
                12884901889,
                0
            ],
            "nQuads": 218,
            "nMops": 528
        },
        "...MASTER...": {
            "start_perf": [
                0.325469970703125,
                0.082772999999999999,
                0.038627000000000002,
                321568,
                321604,
                1665984529.6664219,
                894389826678021
            ],
            "child_modules": {
                "__simulation_def": 1,
                "std": 1,
                "Mem1r1w": 1
            },
            "end_perf": [
                0.32823610305786133,
                0.084657999999999997,
                0.039507,
                322548,
                322548,
                894389836642771,
                0,
                0
            ],
            "nQuads": 3,
            "nMops": 5,
            "nRouts": 7
        },
        "Mem1r1w": {
            "start_perf": [
                0.33725118637084961,
                0.092647999999999994,
                0.040533,
                323512,
                323512,
                1665984529.6782031,
                894389869038881
            ],
            "child_modules": {},
            "Compiled": "Yes",
            "nRouts": 26,
            "Compiled Times": 1,
            "end_perf": [
                0.34167599678039551,
                0.095725000000000005,
                0.041880000000000001,
                323656,
                323656,
                894389885033265,
                17179869185,
                0
            ],
            "nQuads": 134,
            "nMops": 338
        },
        "__simulation_def": {
            "start_perf": [
                0.34171700477600098,
                0.095755000000000007,
                0.041891999999999999,
                323656,
                323656,
                1665984529.6826689,
                894389885111445
            ],
            "child_modules": {},
            "Compiled": "Yes",
            "nRouts": 8,
            "Compiled Times": 1,
            "end_perf": [
                0.3429570198059082,
                0.096616999999999995,
                0.042270000000000002,
                323656,
                323656,
                894389889613563,
                21474836481,
                0
            ],
            "nQuads": 16,
            "nMops": 17
        }
    },
    "reusePaths": {},
    "ObjArchives": [
        {
            "archive": "archive.0/_44089_archive_1.a",
            "objects": [
                [
                    "reYIK_d.o",
                    43064
                ],
                [
                    "J54Lv_d.o",
                    11574
                ],
                [
                    "U3bwm_d.o",
                    9002
                ],
                [
                    "amcQwB.o",
                    129104
                ]
            ],
            "size": 192744
        }
    ],
    "stat": {
        "ru_self_end": {
            "ru_utime_sec": 0.099947999999999995,
            "ru_nivcsw": 1,
            "ru_stime_sec": 0.043727000000000002,
            "ru_maxrss_kb": 137244,
            "ru_nvcsw": 59,
            "ru_minflt": 12965,
            "ru_majflt": 0
        },
        "ru_childs_end": {
            "ru_utime_sec": 0.116934,
            "ru_nivcsw": 5,
            "ru_stime_sec": 0.078185000000000004,
            "ru_maxrss_kb": 137244,
            "ru_nvcsw": 47,
            "ru_minflt": 11545,
            "ru_majflt": 0
        },
        "cpu_cycles_end": 894390316298559,
        "peak_mem_kb": 323692
    }
}